tree_sitter_fluentbit/__init__.pyi
tree_sitter_fluentbit/__init__.py
tree_sitter_fluentbit/py.typed
tree_sitter_fluentbit/binding.c
tree_sitter_fluentbit/_binding.abi3.so
tree_sitter_fluentbit/queries/highlights.scm
tree_sitter_fluentbit-0.1.0.dist-info/LICENSE
tree_sitter_fluentbit-0.1.0.dist-info/METADATA
tree_sitter_fluentbit-0.1.0.dist-info/top_level.txt
tree_sitter_fluentbit-0.1.0.dist-info/RECORD
tree_sitter_fluentbit-0.1.0.dist-info/WHEEL
