Metadata-Version: 2.1
Name: tree-sitter-fluentbit
Version: 0.1.0
Summary: Fluentbit grammar for tree-sitter
License: MIT
Project-URL: Homepage, https://github.com/tree-sitter/tree-sitter-fluentbit
Keywords: incremental,parsing,tree-sitter,fluentbit
Classifier: Intended Audience :: Developers
Classifier: License :: OSI Approved :: MIT License
Classifier: Topic :: Software Development :: Compilers
Classifier: Topic :: Text Processing :: Linguistic
Classifier: Typing :: Typed
Requires-Python: >=3.9
License-File: LICENSE
Provides-Extra: core
Requires-Dist: tree-sitter~=0.21; extra == "core"
